{
  "img_name": "frankfurt_000001_043564_leftImg8bit.png",
  "height": 1024,
  "width": 2048,
  "depth": 3,
  "object": [
    {
      "class": "car",
      "x1": 1153,
      "y1": 398,
      "x2": 1206,
      "y2": 434
    },
    {
      "class": "person",
      "x1": 1452,
      "y1": 369,
      "x2": 1490,
      "y2": 455
    },
    {
      "class": "car",
      "x1": 961,
      "y1": 390,
      "x2": 1025,
      "y2": 444
    },
    {
      "class": "car",
      "x1": 926,
      "y1": 397,
      "x2": 991,
      "y2": 450
    },
    {
      "class": "car",
      "x1": 867,
      "y1": 391,
      "x2": 958,
      "y2": 461
    },
    {
      "class": "car",
      "x1": 716,
      "y1": 355,
      "x2": 873,
      "y2": 480
    },
    {
      "class": "car",
      "x1": 369,
      "y1": 389,
      "x2": 639,
      "y2": 531
    }
  ]
}