{
  "img_name": "frankfurt_000001_010600_leftImg8bit.png",
  "height": 1024,
  "width": 2048,
  "depth": 3,
  "object": [
    {
      "class": "rider",
      "x1": 936,
      "y1": 374,
      "x2": 966,
      "y2": 446
    },
    {
      "class": "bike",
      "x1": 939,
      "y1": 409,
      "x2": 964,
      "y2": 461
    },
    {
      "class": "car",
      "x1": 879,
      "y1": 388,
      "x2": 936,
      "y2": 455
    },
    {
      "class": "car",
      "x1": 721,
      "y1": 381,
      "x2": 840,
      "y2": 487
    },
    {
      "class": "person",
      "x1": 91,
      "y1": 329,
      "x2": 148,
      "y2": 373
    },
    {
      "class": "car",
      "x1": 312,
      "y1": 218,
      "x2": 755,
      "y2": 611
    },
    {
      "class": "car",
      "x1": 0,
      "y1": 359,
      "x2": 504,
      "y2": 723
    },
    {
      "class": "car",
      "x1": 0,
      "y1": 524,
      "x2": 57,
      "y2": 829
    },
    {
      "class": "person",
      "x1": 828,
      "y1": 349,
      "x2": 869,
      "y2": 507
    },
    {
      "class": "bus",
      "x1": 1072,
      "y1": 382,
      "x2": 1126,
      "y2": 423
    },
    {
      "class": "car",
      "x1": 1208,
      "y1": 385,
      "x2": 1300,
      "y2": 465
    },
    {
      "class": "car",
      "x1": 1223,
      "y1": 393,
      "x2": 1334,
      "y2": 473
    },
    {
      "class": "person",
      "x1": 1502,
      "y1": 359,
      "x2": 1558,
      "y2": 474
    },
    {
      "class": "person",
      "x1": 1596,
      "y1": 356,
      "x2": 1648,
      "y2": 471
    },
    {
      "class": "person",
      "x1": 1776,
      "y1": 373,
      "x2": 1855,
      "y2": 457
    },
    {
      "class": "person",
      "x1": 1844,
      "y1": 374,
      "x2": 1889,
      "y2": 451
    },
    {
      "class": "person",
      "x1": 1136,
      "y1": 395,
      "x2": 1165,
      "y2": 460
    }
  ]
}